mlrl/__init__.py
mlrl/common/__init__.py
mlrl/common/learners.py
mlrl/common/mixins.py
mlrl/common/package_info.py
mlrl/common/config/__init__.py
mlrl/common/config/parameters.py
mlrl/common/cython/__init__.py
mlrl/common/cython/example_weights.cpython-312-aarch64-linux-musl.so
mlrl/common/cython/feature_binning.cpython-312-aarch64-linux-musl.so
mlrl/common/cython/feature_info.cpython-312-aarch64-linux-musl.so
mlrl/common/cython/feature_matrix.cpython-312-aarch64-linux-musl.so
mlrl/common/cython/feature_sampling.cpython-312-aarch64-linux-musl.so
mlrl/common/cython/instance_sampling.cpython-312-aarch64-linux-musl.so
mlrl/common/cython/label_matrix.cpython-312-aarch64-linux-musl.so
mlrl/common/cython/learner.cpython-312-aarch64-linux-musl.so
mlrl/common/cython/learner_classification.cpython-312-aarch64-linux-musl.so
mlrl/common/cython/learner_regression.cpython-312-aarch64-linux-musl.so
mlrl/common/cython/libmlrlcommon.so
mlrl/common/cython/libmlrlcommon.so.0
mlrl/common/cython/libmlrlcommon.so.0.15.1
mlrl/common/cython/multi_threading.cpython-312-aarch64-linux-musl.so
mlrl/common/cython/output_matrix.cpython-312-aarch64-linux-musl.so
mlrl/common/cython/output_sampling.cpython-312-aarch64-linux-musl.so
mlrl/common/cython/output_space_info.cpython-312-aarch64-linux-musl.so
mlrl/common/cython/package_info.cpython-312-aarch64-linux-musl.so
mlrl/common/cython/partition_sampling.cpython-312-aarch64-linux-musl.so
mlrl/common/cython/post_optimization.cpython-312-aarch64-linux-musl.so
mlrl/common/cython/prediction.cpython-312-aarch64-linux-musl.so
mlrl/common/cython/probability_calibration.cpython-312-aarch64-linux-musl.so
mlrl/common/cython/regression_matrix.cpython-312-aarch64-linux-musl.so
mlrl/common/cython/rng.cpython-312-aarch64-linux-musl.so
mlrl/common/cython/rule_induction.cpython-312-aarch64-linux-musl.so
mlrl/common/cython/rule_model.cpython-312-aarch64-linux-musl.so
mlrl_common-0.15.1.dist-info/METADATA
mlrl_common-0.15.1.dist-info/WHEEL
mlrl_common-0.15.1.dist-info/top_level.txt
mlrl_common-0.15.1.dist-info/RECORD
mlrl_common-0.15.1.dist-info/sboms/auditwheel.cdx.json
