Metadata-Version: 2.4
Name: mlrl-common
Version: 0.15.1
Summary: Provides common modules to be used by different types of multi-label rule learning algorithms
Author-email: Michael Rapp <michael.rapp.ml@gmail.com>
License-Expression: MIT
Project-URL: homepage, https://github.com/mrapp-ke/MLRL-Boomer
Project-URL: source, https://github.com/mrapp-ke/MLRL-Boomer.git
Project-URL: download, https://github.com/mrapp-ke/MLRL-Boomer/releases
Project-URL: changelog, https://raw.githubusercontent.com/mrapp-ke/MLRL-Boomer/refs/heads/main/CHANGELOG.md
Project-URL: documentation, https://mlrl-boomer.readthedocs.io/en/latest
Project-URL: issues, https://github.com/mrapp-ke/MLRL-Boomer/issues
Keywords: machine learning,multi-label classification,multi-output regression,multi-target regression,rule learning,scikit-learn
Classifier: Development Status :: 5 - Production/Stable
Classifier: Intended Audience :: Developers
Classifier: Operating System :: MacOS
Classifier: Operating System :: Microsoft :: Windows
Classifier: Operating System :: POSIX :: Linux
Classifier: Programming Language :: C++
Classifier: Programming Language :: Cython
Classifier: Programming Language :: Python :: 3
Classifier: Topic :: Scientific/Engineering :: Artificial Intelligence
Classifier: Topic :: Software Development :: Libraries :: Python Modules
Requires-Python: >=3.12
Requires-Dist: mlrl-util==0.15.1
Requires-Dist: packaging<26.0,>=25.0
Requires-Dist: scikit-learn<1.9,>=1.8
Provides-Extra: testbed
Requires-Dist: mlrl-testbed-sklearn==0.15.1; extra == "testbed"
